filesinfo/__init__.py
filesinfo/cli.py
filesinfo/core.py
filesinfo/data/external_extensions.json
filesinfo-0.1.2.dist-info/licenses/LICENSE
filesinfo-0.1.2.dist-info/METADATA
filesinfo-0.1.2.dist-info/WHEEL
filesinfo-0.1.2.dist-info/entry_points.txt
filesinfo-0.1.2.dist-info/top_level.txt
filesinfo-0.1.2.dist-info/RECORD
