Metadata-Version: 2.4
Name: filesinfo
Version: 0.1.2
Summary: File extension metadata and platform selection utilities
Author: Cagri Tas
License-Expression: MIT
Project-URL: Homepage, https://github.com/cagritas/filesinfo
Project-URL: Repository, https://github.com/cagritas/filesinfo
Keywords: file,extension,metadata,sandbox
Classifier: Programming Language :: Python :: 3
Classifier: Programming Language :: Python :: 3.9
Classifier: Programming Language :: Python :: 3.10
Classifier: Programming Language :: Python :: 3.11
Classifier: Operating System :: OS Independent
Requires-Python: >=3.9
License-File: LICENSE
Dynamic: license-file
